hs_infra/__init__.py
hs_infra/adapters/__init__.py
hs_infra/adapters/base/__init__.py
hs_infra/adapters/base/base_adapter.py
hs_infra/adapters/email_adapters/__init__.py
hs_infra/adapters/email_adapters/base_email_adapter.py
hs_infra/adapters/message_adapters/__init__.py
hs_infra/adapters/message_adapters/base_message_adapter.py
hs_infra/config/__init__.py
hs_infra/config/runtime_config.py
hs_infra/dal/__init__.py
hs_infra/dal/base/__init__.py
hs_infra/dal/base/base_dal.py
hs_infra/entities/__init__.py
hs_infra/entities/base/__init__.py
hs_infra/entities/base/base_entity.py
hs_infra/enums/__init__.py
hs_infra/enums/base/__init__.py
hs_infra/enums/base/base_enum.py
hs_infra/enums/request/__init__.py
hs_infra/enums/request/request_action_enum.py
hs_infra/enums/request/response_status_enum.py
hs_infra/managers/__init__.py
hs_infra/managers/base/__init__.py
hs_infra/managers/base/base_manager.py
hs_infra/managers/base/base_redis_manager.py
hs_infra/managers/message/__init__.py
hs_infra/managers/message/message_redis_manager.py
hs_infra/meta_classes/__init__.py
hs_infra/meta_classes/singleton_meta_class.py
hs_infra/utils/__init__.py
hs_infra/utils/base_utils.py
hs_infra/utils/date_time_utils.py
hs_infra/utils/mobile_number_utils.py
hs_infra/utils/string_utils.py
hs_infra/utils/utils.py
hs_infra/wrappers/__init__.py
hs_infra/wrappers/request_wrapper.py
hs_infra-0.0.9.dist-info/LICENCE
hs_infra-0.0.9.dist-info/METADATA
hs_infra-0.0.9.dist-info/WHEEL
hs_infra-0.0.9.dist-info/top_level.txt
hs_infra-0.0.9.dist-info/RECORD
