Metadata-Version: 2.1
Name: hs-infra
Version: 0.0.9
Summary: utility and common files in hacker-space projects
Home-page: https://gitlab.com/highborn/hackerspace-software-core-infrastructure.git
Author: Ehsan Sadeghi Neshat
Author-email: ehsun.zz@gmail.com
License: UNKNOWN
Platform: UNKNOWN
Classifier: Development Status :: 3 - Alpha
Classifier: License :: OSI Approved :: GNU General Public License v3 (GPLv3)
Classifier: Operating System :: OS Independent
Classifier: Intended Audience :: Developers
Classifier: Programming Language :: Python :: 3
Classifier: Programming Language :: Python :: 3.5
Classifier: Programming Language :: Python :: 3.6
Classifier: Programming Language :: Python :: 3.7
Requires-Python: >=3.5
